erlenberg/__init__.py
erlenberg/logHandler.py
erlenberg/simpleDatabase.py
erlenberg/winutils/__init__.py
erlenberg/winutils/ps.py
erlenberg-3.1.dist-info/LICENSE
erlenberg-3.1.dist-info/METADATA
erlenberg-3.1.dist-info/WHEEL
erlenberg-3.1.dist-info/top_level.txt
erlenberg-3.1.dist-info/RECORD
